zpaste/__init__.py
zpaste/__main__.py
zpaste/py.typed
zpaste-1.0.0.dist-info/WHEEL
zpaste-1.0.0.dist-info/entry_points.txt
zpaste-1.0.0.dist-info/METADATA
zpaste-1.0.0.dist-info/RECORD
