Metadata-Version: 2.3
Name: zpaste
Version: 1.0.0
Summary: Print clipboard content
Author: Zeev Rotshtein
Author-email: Zeev Rotshtein <zeevro@gmail.com>
Requires-Dist: pyperclip
Requires-Python: >=3.12
